setup.py
pycreeper/__init__.py
pycreeper/engine.py
pycreeper/scheduler.py
pycreeper/spider.py
pycreeper.egg-info/PKG-INFO
pycreeper.egg-info/SOURCES.txt
pycreeper.egg-info/dependency_links.txt
pycreeper.egg-info/requires.txt
pycreeper.egg-info/top_level.txt
pycreeper/conf/__init__.py
pycreeper/conf/default_settings.py
pycreeper/conf/settings.py
pycreeper/downloader/__init__.py
pycreeper/downloader_middlewares/__init__.py
pycreeper/downloader_middlewares/cookies_middlewares.py
pycreeper/downloader_middlewares/middlewares.py
pycreeper/http/__init__.py
pycreeper/http/request.py
pycreeper/http/response.py
pycreeper/utils/__init__.py
pycreeper/utils/datatypes.py
pycreeper/utils/exceptions.py
pycreeper/utils/gevent_wrapper.py
pycreeper/utils/hash.py
pycreeper/utils/log.py