Metadata-Version: 1.0
Name: pycreeper
Version: 1.0.0
Summary: A web crawler that is able to crawl dynamic web page.
Home-page: https://github.com/ZcyAndWt/pyCreeper
Author: zcy
Author-email: zhengchenyu.backend@gmail.com
License: LGPL
Platform: UNKNOWN
